MANIFEST.in
README.md
requirements.txt
setup.py
ebaipy/__init__.py
ebaipy/exceptions.py
ebaipy/utils.py
ebaipy.egg-info/PKG-INFO
ebaipy.egg-info/SOURCES.txt
ebaipy.egg-info/dependency_links.txt
ebaipy.egg-info/requires.txt
ebaipy.egg-info/top_level.txt
ebaipy/client/__init__.py
ebaipy/client/base.py
ebaipy/client/api/__init__.py
ebaipy/client/api/base.py
ebaipy/client/api/common.py
ebaipy/client/api/marketing.py
ebaipy/client/api/order.py
ebaipy/client/api/shop.py
ebaipy/client/api/sku.py
tests/__init__.py
tests/test_client.py
tests/__pycache__/__init__.cpython-34.pyc
tests/__pycache__/test_client.cpython-34.pyc